{"StimulationName": "Threshold Protocol", "StimulationSequence": [{"Duration": 30, "StimulationType": "Baseline", "RecordingFilename": "Baseline", "StimulationLead": 0, "StimulationChannel": [0], "StimulationReturn": -1}, {"Duration": 10, "StimulationType": "Novel", "StimulationIndex": 3, "RecordingFilename": "ERNA", "StimulationLead": 0, "StimulationChannel": [0], "StimulationReturn": -1}, {"Duration": 2, "StimulationType": "Baseline", "RecordingFilename": "ERNA", "StimulationLead": 0, "StimulationChannel": [0], "StimulationReturn": -1}, {"Duration": 10, "StimulationType": "Novel", "StimulationIndex": 3, "RecordingFilename": "ERNA", "StimulationLead": 0, "StimulationChannel": [1], "StimulationReturn": -1}, {"Duration": 2, "StimulationType": "Baseline", "RecordingFilename": "ERNA", "StimulationLead": 0, "StimulationChannel": [0], "StimulationReturn": -1}, {"Duration": 10, "StimulationType": "Novel", "StimulationIndex": 3, "RecordingFilename": "ERNA", "StimulationLead": 0, "StimulationChannel": [2], "StimulationReturn": -1}, {"Duration": 2, "StimulationType": "Baseline", "RecordingFilename": "ERNA", "StimulationLead": 0, "StimulationChannel": [0], "StimulationReturn": -1}, {"Duration": 10, "StimulationType": "Novel", "StimulationIndex": 3, "RecordingFilename": "ERNA", "StimulationLead": 0, "StimulationChannel": [3], "StimulationReturn": -1}, {"Duration": 2, "StimulationType": "Baseline", "RecordingFilename": "ERNA", "StimulationLead": 0, "StimulationChannel": [0], "StimulationReturn": -1}, {"Duration": 10, "StimulationType": "Novel", "StimulationIndex": 3, "RecordingFilename": "ERNA", "StimulationLead": 0, "StimulationChannel": [4], "StimulationReturn": -1}, {"Duration": 2, "StimulationType": "Baseline", "RecordingFilename": "ERNA", "StimulationLead": 0, "StimulationChannel": [0], "StimulationReturn": -1}, {"Duration": 10, "StimulationType": "Novel", "StimulationIndex": 3, "RecordingFilename": "ERNA", "StimulationLead": 0, "StimulationChannel": [5], "StimulationReturn": -1}, {"Duration": 2, "StimulationType": "Baseline", "RecordingFilename": "ERNA", "StimulationLead": 0, "StimulationChannel": [0], "StimulationReturn": -1}, {"Duration": 10, "StimulationType": "Novel", "StimulationIndex": 3, "RecordingFilename": "ERNA", "StimulationLead": 0, "StimulationChannel": [6], "StimulationReturn": -1}, {"Duration": 2, "StimulationType": "Baseline", "RecordingFilename": "ERNA", "StimulationLead": 0, "StimulationChannel": [0], "StimulationReturn": -1}, {"Duration": 10, "StimulationType": "Novel", "StimulationIndex": 3, "RecordingFilename": "ERNA", "StimulationLead": 0, "StimulationChannel": [7], "StimulationReturn": -1}, {"Duration": 2, "StimulationType": "Baseline", "RecordingFilename": "ERNA", "StimulationLead": 0, "StimulationChannel": [0], "StimulationReturn": -1}, {"Duration": 10, "StimulationType": "Standard", "RecordingFilename": "EP", "StimulationLead": 0, "StimulationChannel": [0], "StimulationReturn": -1, "Amplitude": 2.0, "Pulsewidth": 90, "Frequency": 10}, {"Duration": 2, "StimulationType": "Baseline", "RecordingFilename": "EP", "StimulationLead": 0, "StimulationChannel": [0], "StimulationReturn": -1}, {"Duration": 10, "StimulationType": "Standard", "RecordingFilename": "EP", "StimulationLead": 0, "StimulationChannel": [1], "StimulationReturn": -1, "Amplitude": 2.0, "Pulsewidth": 90, "Frequency": 10}, {"Duration": 2, "StimulationType": "Baseline", "RecordingFilename": "EP", "StimulationLead": 0, "StimulationChannel": [0], "StimulationReturn": -1}, {"Duration": 10, "StimulationType": "Standard", "RecordingFilename": "EP", "StimulationLead": 0, "StimulationChannel": [2], "StimulationReturn": -1, "Amplitude": 2.0, "Pulsewidth": 90, "Frequency": 10}, {"Duration": 2, "StimulationType": "Baseline", "RecordingFilename": "EP", "StimulationLead": 0, "StimulationChannel": [0], "StimulationReturn": -1}, {"Duration": 10, "StimulationType": "Standard", "RecordingFilename": "EP", "StimulationLead": 0, "StimulationChannel": [3], "StimulationReturn": -1, "Amplitude": 2.0, "Pulsewidth": 90, "Frequency": 10}, {"Duration": 2, "StimulationType": "Baseline", "RecordingFilename": "EP", "StimulationLead": 0, "StimulationChannel": [0], "StimulationReturn": -1}, {"Duration": 10, "StimulationType": "Standard", "RecordingFilename": "EP", "StimulationLead": 0, "StimulationChannel": [4], "StimulationReturn": -1, "Amplitude": 2.0, "Pulsewidth": 90, "Frequency": 10}, {"Duration": 2, "StimulationType": "Baseline", "RecordingFilename": "EP", "StimulationLead": 0, "StimulationChannel": [0], "StimulationReturn": -1}, {"Duration": 10, "StimulationType": "Standard", "RecordingFilename": "EP", "StimulationLead": 0, "StimulationChannel": [5], "StimulationReturn": -1, "Amplitude": 2.0, "Pulsewidth": 90, "Frequency": 10}, {"Duration": 2, "StimulationType": "Baseline", "RecordingFilename": "EP", "StimulationLead": 0, "StimulationChannel": [0], "StimulationReturn": -1}, {"Duration": 10, "StimulationType": "Standard", "RecordingFilename": "EP", "StimulationLead": 0, "StimulationChannel": [6], "StimulationReturn": -1, "Amplitude": 2.0, "Pulsewidth": 90, "Frequency": 10}, {"Duration": 2, "StimulationType": "Baseline", "RecordingFilename": "EP", "StimulationLead": 0, "StimulationChannel": [0], "StimulationReturn": -1}, {"Duration": 10, "StimulationType": "Standard", "RecordingFilename": "EP", "StimulationLead": 0, "StimulationChannel": [7], "StimulationReturn": -1, "Amplitude": 2.0, "Pulsewidth": 90, "Frequency": 10}, {"Duration": 2, "StimulationType": "Baseline", "RecordingFilename": "EP", "StimulationLead": 0, "StimulationChannel": [0], "StimulationReturn": -1}], "AnalogWaveforms": ["ProbeStim/Probe60.bin", "ProbeStim/Probe90.bin", "ProbeStim/Probe120.bin", "ProbeStim/Probe150.bin", "ProbeStim/Probe180.bin"]}